word2emoji/__init__.py
word2emoji/create_db.py
word2emoji/flatten_db.py
word2emoji/flattened.txt
word2emoji/lookup.py
word2emoji/stem_db.jsz2
word2emoji/text_to_training.py
word2emoji/training.txt
word2emoji/wiki-100k.txt
word2emoji/words.json
word2emoji-0.1.5.dist-info/LICENSE
word2emoji-0.1.5.dist-info/METADATA
word2emoji-0.1.5.dist-info/WHEEL
word2emoji-0.1.5.dist-info/top_level.txt
word2emoji-0.1.5.dist-info/RECORD
