Metadata-Version: 2.1
Name: word2emoji
Version: 0.1.5
Summary: Convert any word in the English language to an emoji
Author-email: Douwe Osinga <douwe.osinga@gmail.com>
License: MIT License        
Project-URL: Documentation, https://github.com/DOsinga/word2emoji#readme
Project-URL: Issues, https://github.com/DOsinga/word2emoji/issues
Project-URL: Source, https://github.com/DOsinga/word2emoji
Keywords: emoji,nlp,text
Classifier: Development Status :: 4 - Beta
Classifier: Programming Language :: Python
Classifier: Programming Language :: Python :: 3.7
Classifier: Programming Language :: Python :: 3.8
Classifier: Programming Language :: Python :: 3.9
Classifier: Programming Language :: Python :: 3.10
Classifier: Programming Language :: Python :: Implementation :: CPython
Classifier: Programming Language :: Python :: Implementation :: PyPy
Requires-Python: >=3.7
License-File: LICENSE
Requires-Dist: nltk
